{"AndroidX lifecycle common library": {"length": 10694, "start": 38}, "AndroidX lifecycle livedatacore library": {"length": 10694, "start": 10776}, "AndroidX lifecycle runtime library": {"length": 10694, "start": 21509}, "Animal Sniffer": {"length": 1096, "start": 32222}, "Checker Framework Annotations": {"length": 1892, "start": 33352}, "Checker Framework Utilities": {"length": 1125, "start": 35276}, "Error Prone": {"length": 11357, "start": 36417}, "Firebase": {"length": 11357, "start": 47787}, "Google Auto": {"length": 11358, "start": 59160}, "Guava JDK5": {"length": 11358, "start": 70533}, "Guava JDK7": {"length": 11362, "start": 81906}, "J2ObjC": {"length": 13064, "start": 93279}, "JSR 250": {"length": 11358, "start": 106355}, "JSR 305": {"length": 1602, "start": 117725}, "JSR 330": {"length": 11365, "start": 119339}, "JSpecify": {"length": 11358, "start": 164141}, "JsInterop Annotations": {"length": 11307, "start": 130730}, "SafeParcelable library": {"length": 11358, "start": 142064}, "apksig": {"length": 10695, "start": 153433}}